{"v":4,"entries":{"mantine-button--docs":{"id":"mantine-button--docs","title":"Mantine/Button","name":"Docs","importPath":"./src/stories/Button.stories.ts","type":"docs","tags":["autodocs","docs"],"storiesImports":[]},"mantine-button--primary":{"id":"mantine-button--primary","title":"Mantine/Button","name":"Primary","importPath":"./src/stories/Button.stories.ts","tags":["autodocs","story"],"type":"story"},"mantine-button--outline":{"id":"mantine-button--outline","title":"Mantine/Button","name":"Outline","importPath":"./src/stories/Button.stories.ts","tags":["autodocs","story"],"type":"story"},"mantine-button--large":{"id":"mantine-button--large","title":"Mantine/Button","name":"Large","importPath":"./src/stories/Button.stories.ts","tags":["autodocs","story"],"type":"story"},"mantine-button--small":{"id":"mantine-button--small","title":"Mantine/Button","name":"Small","importPath":"./src/stories/Button.stories.ts","tags":["autodocs","story"],"type":"story"},"mantine-button--compact":{"id":"mantine-button--compact","title":"Mantine/Button","name":"Compact","importPath":"./src/stories/Button.stories.ts","tags":["autodocs","story"],"type":"story"},"mantine-switch--docs":{"id":"mantine-switch--docs","title":"Mantine/Switch","name":"Docs","importPath":"./src/stories/Switch.stories.ts","type":"docs","tags":["autodocs","docs"],"storiesImports":[]},"mantine-switch--primary":{"id":"mantine-switch--primary","title":"Mantine/Switch","name":"Primary","importPath":"./src/stories/Switch.stories.ts","tags":["autodocs","story"],"type":"story"}}}
